AUTHORS.md
CHANGELOG.md
CONTRIBUTING.md
DEVELOPMENT.md
LICENSE
pearllib/__init__.py
pearllib/exceptions.py
pearllib/messenger.py
pearllib/models.py
pearllib/package.py
pearllib/parser.py
pearllib/pearl.py
pearllib/pearlenv.py
pearllib/static/boot/emacs/pearl.el
pearllib/static/boot/fish/pearl.fish
pearllib/static/boot/sh/pearl.sh
pearllib/static/boot/vim/pearl.vim
pearllib/static/buava/.git
pearllib/static/buava/.gitmodules
pearllib/static/buava/.travis.yml
pearllib/static/buava/CONTRIBUTING.md
pearllib/static/buava/LICENSE
pearllib/static/buava/README.md
pearllib/static/buava/lib/osx-compat.fish
pearllib/static/buava/lib/osx-compat.sh
pearllib/static/buava/lib/trycatch.sh
pearllib/static/buava/lib/utils.sh
pearllib/static/builtins/utils.sh
pearllib/static/templates/pearl-config.template/config.bash
pearllib/static/templates/pearl-config.template/config.el
pearllib/static/templates/pearl-config.template/config.fish
pearllib/static/templates/pearl-config.template/config.sh
pearllib/static/templates/pearl-config.template/config.vim
pearllib/static/templates/pearl-config.template/config.zsh
pearllib/static/templates/pearl-config.template/hooks.sh
pearllib/static/templates/pearl-config.template/package.conf
pearllib/static/templates/pearl.conf.template
pearllib/system.py
pearllib/utils.py
pearl-2.3.12.dist-info/LICENSE
pearl-2.3.12.dist-info/METADATA
pearl-2.3.12.dist-info/WHEEL
pearl-2.3.12.dist-info/entry_points.txt
pearl-2.3.12.dist-info/RECORD
