Metadata-Version: 2.1
Name: pearl
Version: 2.3.12
Summary: Pearl is a lightweight package manager for automating reproducible environments between different systems (Linux and OSX). It can be used for dotfiles, plugins, programs and any form of code accessible via git.
Home-page: http://github.com/pearl-core/pearl
License: GPL-3.0-only
Keywords: pearl,shell,dotfiles,package manager
Author: Filippo Squillace
Author-email: feel.sqoox@amazon.com
Requires-Python: >=3.7,<4.0
Classifier: Development Status :: 5 - Production/Stable
Classifier: Intended Audience :: Developers
Classifier: License :: OSI Approved :: GNU General Public License v3 (GPLv3)
Classifier: Natural Language :: English
Classifier: Operating System :: MacOS
Classifier: Operating System :: POSIX :: Linux
Classifier: Programming Language :: Python :: 3
Classifier: Programming Language :: Python :: 3.7
Classifier: Programming Language :: Python :: 3.8
Classifier: Programming Language :: Python :: 3.9
Classifier: Programming Language :: Python :: 3.10
Classifier: Programming Language :: Python :: 3.11
Classifier: Topic :: Software Development :: Build Tools
Classifier: Topic :: System :: Shells
Classifier: Topic :: System :: Software Distribution
Classifier: Topic :: Utilities
Requires-Dist: importlib-metadata (>=4.12.0,<5.0.0)
Project-URL: Repository, https://github.com/pearl-core/pearl/releases
